README.md
setup.py
artifactz/__init__.py
artifactz/artifact_registry.py
artifactz/gcs_artifact_registry.py
artifactz/main.py
artifactz.egg-info/PKG-INFO
artifactz.egg-info/SOURCES.txt
artifactz.egg-info/dependency_links.txt
artifactz.egg-info/top_level.txt
tests/__init__.py
tests/test_artifact_registry.py
tests/test_gcs_artifact_registry.py