Metadata-Version: 2.1
Name: artifactz
Version: 0.0.2.0
Summary: DO NOT USE - This is a sample program
Home-page: https://github.com/hashmapinc/artifactz
Author: Hashmap, and NTT DATA Services Company
Author-email: accelerators@hashmapinc.com
License: UNKNOWN
Platform: UNKNOWN
Classifier: Programming Language :: Python :: 3
Classifier: License :: OSI Approved :: Apache Software License
Classifier: Operating System :: OS Independent
Classifier: Development Status :: 4 - Beta
Requires-Python: >=3.6
